tn/__init__.py
tn-0.0.5.dist-info/licenses/LICENSE
tn-0.0.5.dist-info/METADATA
tn-0.0.5.dist-info/WHEEL
tn-0.0.5.dist-info/top_level.txt
tn-0.0.5.dist-info/RECORD
